odoo/addons/l10n_fr_chorus_facturx/README.rst
odoo/addons/l10n_fr_chorus_facturx/__init__.py
odoo/addons/l10n_fr_chorus_facturx/__manifest__.py
odoo/addons/l10n_fr_chorus_facturx/i18n/fr.po
odoo/addons/l10n_fr_chorus_facturx/i18n/l10n_fr_chorus_factur-x.pot
odoo/addons/l10n_fr_chorus_facturx/i18n/l10n_fr_chorus_facturx.pot
odoo/addons/l10n_fr_chorus_facturx/i18n/nb_NO.po
odoo/addons/l10n_fr_chorus_facturx/models/.ubl.py.swo
odoo/addons/l10n_fr_chorus_facturx/models/__init__.py
odoo/addons/l10n_fr_chorus_facturx/models/account_invoice.py
odoo/addons/l10n_fr_chorus_facturx/models/chorus_flow.py
odoo/addons/l10n_fr_chorus_facturx/models/company.py
odoo/addons/l10n_fr_chorus_facturx/readme/CONFIGURE.rst
odoo/addons/l10n_fr_chorus_facturx/readme/CONTRIBUTORS.rst
odoo/addons/l10n_fr_chorus_facturx/readme/DESCRIPTION.rst
odoo/addons/l10n_fr_chorus_facturx/readme/USAGE.rst
odoo/addons/l10n_fr_chorus_facturx/static/description/icon.png
odoo/addons/l10n_fr_chorus_facturx/static/description/index.html
odoo12_addon_l10n_fr_chorus_facturx-12.0.1.0.2.dist-info/METADATA
odoo12_addon_l10n_fr_chorus_facturx-12.0.1.0.2.dist-info/WHEEL
odoo12_addon_l10n_fr_chorus_facturx-12.0.1.0.2.dist-info/top_level.txt
odoo12_addon_l10n_fr_chorus_facturx-12.0.1.0.2.dist-info/RECORD
