Metadata-Version: 2.1
Name: odoo12-addon-l10n-fr-chorus-facturx
Version: 12.0.1.0.2
Summary: Generate Chorus-compliant Factur-X invoices
Home-page: https://github.com/OCA/l10n-france
Author: Akretion,Odoo Community Association (OCA)
Author-email: support@odoo-community.org
License: AGPL-3
Platform: UNKNOWN
Classifier: Programming Language :: Python
Classifier: Framework :: Odoo
Classifier: License :: OSI Approved :: GNU Affero General Public License v3
Requires-Python: >=3.5
Requires-Dist: odoo12-addon-l10n-fr-account-invoice-facturx
Requires-Dist: odoo12-addon-l10n-fr-chorus-account
Requires-Dist: odoo (<12.1dev,>=12.0a)
